bigtalk/brokers.py
bigtalk/command.py
bigtalk/defines.py
bigtalk/handler.py
bigtalk/message.py
bigtalk/methods.py
bigtalk/objects.py
bigtalk/package.py
bigtalk/persist.py
bigtalk/runtime.py
bigtalk/threads.py
bigtalk/utility.py
bigtalk/modules/__init__.py
bigtalk/modules/atr.py
bigtalk/modules/flt.py
bigtalk/modules/fnd.py
bigtalk/modules/irc.py
bigtalk/modules/log.py
bigtalk/modules/mbx.py
bigtalk/modules/mdl.py
bigtalk/modules/pth.py
bigtalk/modules/req.py
bigtalk/modules/rss.py
bigtalk/modules/rst.py
bigtalk/modules/sil.py
bigtalk/modules/slg.py
bigtalk/modules/tdo.py
bigtalk/modules/thr.py
bigtalk/modules/tmr.py
bigtalk/modules/udp.py
bigtalk/modules/upt.py
bigtalk/modules/wdr.py
bigtalk/modules/web.py
bigtalk/modules/wsd.py
bigtalk/nucleus/__init__.py
bigtalk/nucleus/about.html
bigtalk/nucleus/evidence.html
bigtalk/nucleus/genindex-all.html
bigtalk/nucleus/genindex.html
bigtalk/nucleus/guilty.html
bigtalk/nucleus/index.html
bigtalk/nucleus/manual.html
bigtalk/nucleus/objects.inv
bigtalk/nucleus/pubchem.html
bigtalk/nucleus/reconsider.html
bigtalk/nucleus/request.html
bigtalk/nucleus/robots.txt
bigtalk/nucleus/search.html
bigtalk/nucleus/searchindex.js
bigtalk/nucleus/writings.html
bigtalk/nucleus/_images/ECHAabilify.png
bigtalk/nucleus/_images/ECHAclozapine.png
bigtalk/nucleus/_images/ECHAhaldol.png
bigtalk/nucleus/_images/ECHAzyprexa.png
bigtalk/nucleus/_images/OTP111.png
bigtalk/nucleus/_images/OTP222.png
bigtalk/nucleus/_images/abilifypubchem.png
bigtalk/nucleus/_images/ack3.png
bigtalk/nucleus/_images/bevestigd.jpg
bigtalk/nucleus/_images/clozapinepubchem.png
bigtalk/nucleus/_images/genocide.png
bigtalk/nucleus/_images/haldolpubchem.png
bigtalk/nucleus/_images/informed.jpg
bigtalk/nucleus/_images/kamer2.png
bigtalk/nucleus/_images/skull3.png
bigtalk/nucleus/_images/zyprexapubchem.png
bigtalk/nucleus/_static/alabaster.css
bigtalk/nucleus/_static/basic.css
bigtalk/nucleus/_static/custom.css
bigtalk/nucleus/_static/doctools.js
bigtalk-5.dist-info/METADATA
bigtalk-5.dist-info/WHEEL
bigtalk-5.dist-info/top_level.txt
bigtalk-5.dist-info/RECORD
