Metadata-Version: 2.4
Name: bigtalk
Version: 5
Summary: Big Talk
Author-email: Bart <bthate@dds.nl>
License-Expression: Unlicense
Project-URL: home, https://pypi.org/project/bigtalk
Project-URL: bugs, https://github.com/nixtniet/bigtalk/issues
Project-URL: source, https://github.com/nixtniet/bigtalk
Classifier: Development Status :: 3 - Alpha
Classifier: Operating System :: Unix
Classifier: Programming Language :: Python :: 3
Classifier: Topic :: Utilities
